{
  "date": "2020-3-13",
  "version": "1.2.8",
  "elapsedSeconds": 1.05,
  "metaAnalyze": {
    "folderPath": "D:\\ManaZeak\\Assets\\Quality\\",
    "dateFrom": "2019-3-6",
    "dateTo": "2020-3-4",
    "sizeDelta": 826753193737,
    "filesDelta": 30977,
    "foldersDelta": 5036,
    "flacDelta": 27517,
    "mp3Delta": -1121,
    "jpgDelta": 4583,
    "pngDelta": 0,
    "flacPercentageDelta": 12.170000000000002,
    "mp3PercentageDelta": -12.17,
    "jpgPercentageDelta": 0.0,
    "pngPercentageDelta": 0.0,
    "artistsDelta": 455,
    "albumsDelta": 4580,
    "tracksDelta": 26396,
    "coversDelta": 4583,
    "errorsDelta": 0,
    "possibleErrorsDelta": 861654,
    "purityDelta": 0.0
  },
  "dumps": [
    {
      "date": "2019-3-6",
      "version": "1.0.0",
      "elapsedSeconds": 0,
      "folderInfo": {
        "name": "/home/messmaker/Data/ManaZeak/Music/_ManaZeakArtists/",
        "files": 10581,
        "folders": 1963,
        "size": 284893326758,
        "flacCount": 8428,
        "mp3Count": 1189,
        "flacPercentage": 87.64,
        "mp3Percentage": 12.36,
        "jpgPercentage": 100.0,
        "pngPercentage": 0.0,
        "jpgCount": 962,
        "pngCount": 0,
        "artistsCount": 999,
        "albumsCount": 965,
        "tracksCount": 9617,
        "coversCount": 962,
        "errorsCount": 0,
        "possibleErrors": 182723,
        "purity": 100.0
      }
    },
    {
      "date": "2019-3-13",
      "version": "1.0.1",
      "elapsedSeconds": 0,
      "folderInfo": {
        "name": "/home/messmaker/Data/ManaZeak/Music/_ManaZeakArtists/",
        "files": 10845,
        "folders": 1994,
        "size": 292700397218,
        "flacCount": 8656,
        "mp3Count": 1197,
        "flacPercentage": 87.85,
        "mp3Percentage": 12.15,
        "jpgPercentage": 100.0,
        "pngPercentage": 0.0,
        "jpgCount": 990,
        "pngCount": 0,
        "artistsCount": 1005,
        "albumsCount": 990,
        "tracksCount": 9853,
        "coversCount": 990,
        "errorsCount": 0,
        "possibleErrors": 206913,
        "purity": 100.0
      }
    },
    {
      "date": "2019-3-20",
      "version": "1.0.2",
      "elapsedSeconds": 0,
      "folderInfo": {
        "name": "/home/messmaker/Data/ManaZeak/Music/_ManaZeakArtists/",
        "files": 10908,
        "folders": 2019,
        "size": 293962904465,
        "flacCount": 8702,
        "mp3Count": 1200,
        "flacPercentage": 87.88,
        "mp3Percentage": 12.12,
        "jpgPercentage": 100.0,
        "pngPercentage": 0.0,
        "jpgCount": 1004,
        "pngCount": 0,
        "artistsCount": 1016,
        "albumsCount": 1004,
        "tracksCount": 9902,
        "coversCount": 1004,
        "errorsCount": 0,
        "possibleErrors": 207942,
        "purity": 100.0
      }
    },
    {
      "date": "2019-3-27",
      "version": "1.0.2",
      "elapsedSeconds": 0,
      "folderInfo": {
        "name": "/home/messmaker/Data/ManaZeak/Music/_ManaZeakArtists/",
        "files": 10915,
        "folders": 2022,
        "size": 294179164201,
        "flacCount": 8710,
        "mp3Count": 1194,
        "flacPercentage": 87.94,
        "mp3Percentage": 12.06,
        "jpgPercentage": 100.0,
        "pngPercentage": 0.0,
        "jpgCount": 1009,
        "pngCount": 0,
        "artistsCount": 1014,
        "albumsCount": 1009,
        "tracksCount": 9904,
        "coversCount": 1009,
        "errorsCount": 0,
        "possibleErrors": 207984,
        "purity": 100.0
      }
    },
    {
      "date": "2019-4-3",
      "version": "1.0.2",
      "elapsedSeconds": 0,
      "folderInfo": {
        "name": "/home/messmaker/Data/ManaZeak/Music/_ManaZeakArtists/",
        "files": 11201,
        "folders": 2057,
        "size": 304331920764,
        "flacCount": 8998,
        "mp3Count": 1152,
        "flacPercentage": 88.65,
        "mp3Percentage": 11.35,
        "jpgPercentage": 100.0,
        "pngPercentage": 0.0,
        "jpgCount": 1049,
        "pngCount": 0,
        "artistsCount": 1009,
        "albumsCount": 1049,
        "tracksCount": 10150,
        "coversCount": 1049,
        "errorsCount": 0,
        "possibleErrors": 213150,
        "purity": 100.0
      }
    },
    {
      "date": "2019-4-10",
      "version": "1.0.2",
      "elapsedSeconds": 0,
      "folderInfo": {
        "name": "/home/messmaker/Data/ManaZeak/Music/_ManaZeakArtists/",
        "files": 11223,
        "folders": 2059,
        "size": 306160968436,
        "flacCount": 9020,
        "mp3Count": 1150,
        "flacPercentage": 88.69,
        "mp3Percentage": 11.31,
        "jpgPercentage": 100.0,
        "pngPercentage": 0.0,
        "jpgCount": 1051,
        "pngCount": 0,
        "artistsCount": 1009,
        "albumsCount": 1051,
        "tracksCount": 10170,
        "coversCount": 1051,
        "errorsCount": 0,
        "possibleErrors": 213570,
        "purity": 100.0
      }
    },
    {
      "date": "2019-4-17",
      "version": "1.0.2",
      "elapsedSeconds": 0,
      "folderInfo": {
        "name": "/home/messmaker/Data/ManaZeak/Music/_ManaZeakArtists/",
        "files": 11367,
        "folders": 2074,
        "size": 310807793708,
        "flacCount": 9165,
        "mp3Count": 1134,
        "flacPercentage": 88.99,
        "mp3Percentage": 11.01,
        "jpgPercentage": 100.0,
        "pngPercentage": 0.0,
        "jpgCount": 1067,
        "pngCount": 0,
        "artistsCount": 1008,
        "albumsCount": 1067,
        "tracksCount": 10299,
        "coversCount": 1067,
        "errorsCount": 0,
        "possibleErrors": 216279,
        "purity": 100.0
      }
    },
    {
      "date": "2019-4-24",
      "version": "1.0.2",
      "elapsedSeconds": 0,
      "folderInfo": {
        "name": "/home/messmaker/Data/ManaZeak/Music/_ManaZeakArtists/",
        "files": 11529,
        "folders": 2094,
        "size": 315967955510,
        "flacCount": 9320,
        "mp3Count": 1124,
        "flacPercentage": 89.24,
        "mp3Percentage": 10.76,
        "jpgPercentage": 100.0,
        "pngPercentage": 0.0,
        "jpgCount": 1084,
        "pngCount": 0,
        "artistsCount": 1011,
        "albumsCount": 1084,
        "tracksCount": 10444,
        "coversCount": 1084,
        "errorsCount": 0,
        "possibleErrors": 219324,
        "purity": 100.0
      }
    },
    {
      "date": "2019-5-1",
      "version": "1.0.2",
      "elapsedSeconds": 0,
      "folderInfo": {
        "name": "/home/messmaker/Data/ManaZeak/Music/_ManaZeakArtists/",
        "files": 10576,
        "folders": 1576,
        "size": 292130281228,
        "flacCount": 9315,
        "mp3Count": 177,
        "flacPercentage": 98.14,
        "mp3Percentage": 1.86,
        "jpgPercentage": 100.0,
        "pngPercentage": 0.0,
        "jpgCount": 1084,
        "pngCount": 0,
        "artistsCount": 493,
        "albumsCount": 1084,
        "tracksCount": 9492,
        "coversCount": 1084,
        "errorsCount": 0,
        "possibleErrors": 199332,
        "purity": 100.0
      }
    },
    {
      "date": "2019-5-8",
      "version": "1.0.2",
      "elapsedSeconds": 0,
      "folderInfo": {
        "name": "/home/messmaker/Data/ManaZeak/Music/_ManaZeakArtists/",
        "files": 11143,
        "folders": 1622,
        "size": 308601239982,
        "flacCount": 9811,
        "mp3Count": 194,
        "flacPercentage": 98.06,
        "mp3Percentage": 1.94,
        "jpgPercentage": 100.0,
        "pngPercentage": 0.0,
        "jpgCount": 1138,
        "pngCount": 0,
        "artistsCount": 485,
        "albumsCount": 1138,
        "tracksCount": 10005,
        "coversCount": 1138,
        "errorsCount": 0,
        "possibleErrors": 220110,
        "purity": 100.0
      }
    },
    {
      "date": "2019-5-15",
      "version": "1.0.2",
      "elapsedSeconds": 0,
      "folderInfo": {
        "name": "/home/messmaker/Data/ManaZeak/Music/_ManaZeakArtists/",
        "files": 11856,
        "folders": 1721,
        "size": 339303816889,
        "flacCount": 10453,
        "mp3Count": 194,
        "flacPercentage": 98.18,
        "mp3Percentage": 1.82,
        "jpgPercentage": 100.0,
        "pngPercentage": 0.0,
        "jpgCount": 1209,
        "pngCount": 0,
        "artistsCount": 513,
        "albumsCount": 1209,
        "tracksCount": 10647,
        "coversCount": 1209,
        "errorsCount": 0,
        "possibleErrors": 234234,
        "purity": 100.0
      }
    },
    {
      "date": "2019-5-22",
      "version": "1.0.2",
      "elapsedSeconds": 0,
      "folderInfo": {
        "name": "/home/messmaker/Data/ManaZeak/Music/_ManaZeakArtists/",
        "files": 12650,
        "folders": 1837,
        "size": 348706164504,
        "flacCount": 11167,
        "mp3Count": 195,
        "flacPercentage": 98.28,
        "mp3Percentage": 1.72,
        "jpgPercentage": 100.0,
        "pngPercentage": 0.0,
        "jpgCount": 1288,
        "pngCount": 0,
        "artistsCount": 551,
        "albumsCount": 1287,
        "tracksCount": 11362,
        "coversCount": 1288,
        "errorsCount": 25,
        "possibleErrors": 249964,
        "purity": 99.99
      }
    },
    {
      "date": "2019-5-29",
      "version": "1.1.0",
      "elapsedSeconds": 0,
      "folderInfo": {
        "name": "/home/messmaker/Data/ManaZeak/Music/_ManaZeakArtists/",
        "files": 12892,
        "folders": 1869,
        "size": 355413088507,
        "flacCount": 11386,
        "mp3Count": 195,
        "flacPercentage": 98.32,
        "mp3Percentage": 1.68,
        "jpgPercentage": 100.0,
        "pngPercentage": 0.0,
        "jpgCount": 1311,
        "pngCount": 0,
        "artistsCount": 559,
        "albumsCount": 1311,
        "tracksCount": 11581,
        "coversCount": 1311,
        "errorsCount": 0,
        "possibleErrors": 312687,
        "purity": 100.0
      }
    },
    {
      "date": "2019-6-5",
      "version": "1.1.0",
      "elapsedSeconds": 0,
      "folderInfo": {
        "name": "/home/messmaker/Data/ManaZeak/Music/_ManaZeakArtists/",
        "files": 13162,
        "folders": 1906,
        "size": 363132244542,
        "flacCount": 11630,
        "mp3Count": 195,
        "flacPercentage": 98.35,
        "mp3Percentage": 1.65,
        "jpgPercentage": 100.0,
        "pngPercentage": 0.0,
        "jpgCount": 1337,
        "pngCount": 0,
        "artistsCount": 570,
        "albumsCount": 1337,
        "tracksCount": 11825,
        "coversCount": 1337,
        "errorsCount": 0,
        "possibleErrors": 319275,
        "purity": 100.0
      }
    },
    {
      "date": "2019-6-12",
      "version": "1.1.0",
      "elapsedSeconds": 0,
      "folderInfo": {
        "name": "/home/messmaker/Data/ManaZeak/Music/_ManaZeakArtists/",
        "files": 13639,
        "folders": 1984,
        "size": 375818939779,
        "flacCount": 12057,
        "mp3Count": 189,
        "flacPercentage": 98.46,
        "mp3Percentage": 1.54,
        "jpgPercentage": 100.0,
        "pngPercentage": 0.0,
        "jpgCount": 1393,
        "pngCount": 0,
        "artistsCount": 592,
        "albumsCount": 1393,
        "tracksCount": 12246,
        "coversCount": 1393,
        "errorsCount": 0,
        "possibleErrors": 330642,
        "purity": 100.0
      }
    },
    {
      "date": "2019-6-19",
      "version": "1.1.0",
      "elapsedSeconds": 0,
      "folderInfo": {
        "name": "/home/messmaker/Data/ManaZeak/Music/_ManaZeakArtists/",
        "files": 13865,
        "folders": 2015,
        "size": 382216482186,
        "flacCount": 12260,
        "mp3Count": 189,
        "flacPercentage": 98.48,
        "mp3Percentage": 1.52,
        "jpgPercentage": 100.0,
        "pngPercentage": 0.0,
        "jpgCount": 1416,
        "pngCount": 0,
        "artistsCount": 600,
        "albumsCount": 1416,
        "tracksCount": 12449,
        "coversCount": 1416,
        "errorsCount": 0,
        "possibleErrors": 336123,
        "purity": 100.0
      }
    },
    {
      "date": "2019-6-26",
      "version": "1.1.0",
      "elapsedSeconds": 0,
      "folderInfo": {
        "name": "/home/messmaker/Data/ManaZeak/Music/_ManaZeakArtists/",
        "files": 14163,
        "folders": 2060,
        "size": 390156482623,
        "flacCount": 12523,
        "mp3Count": 189,
        "flacPercentage": 98.51,
        "mp3Percentage": 1.49,
        "jpgPercentage": 100.0,
        "pngPercentage": 0.0,
        "jpgCount": 1451,
        "pngCount": 0,
        "artistsCount": 610,
        "albumsCount": 1451,
        "tracksCount": 12712,
        "coversCount": 1451,
        "errorsCount": 0,
        "possibleErrors": 343224,
        "purity": 100.0
      }
    },
    {
      "date": "2019-7-3",
      "version": "1.1.0",
      "elapsedSeconds": 0,
      "folderInfo": {
        "name": "/home/messmaker/Data/ManaZeak/Music/_ManaZeakArtists/",
        "files": 14859,
        "folders": 2116,
        "size": 412990432841,
        "flacCount": 13174,
        "mp3Count": 189,
        "flacPercentage": 98.59,
        "mp3Percentage": 1.41,
        "jpgPercentage": 100.0,
        "pngPercentage": 0.0,
        "jpgCount": 1496,
        "pngCount": 0,
        "artistsCount": 622,
        "albumsCount": 1495,
        "tracksCount": 13363,
        "coversCount": 1496,
        "errorsCount": 0,
        "possibleErrors": 360801,
        "purity": 100.0
      }
    },
    {
      "date": "2019-7-10",
      "version": "1.1.0",
      "elapsedSeconds": 0,
      "folderInfo": {
        "name": "/home/messmaker/Data/ManaZeak/Music/_ManaZeakArtists/",
        "files": 15233,
        "folders": 2164,
        "size": 424330077928,
        "flacCount": 13513,
        "mp3Count": 189,
        "flacPercentage": 98.62,
        "mp3Percentage": 1.38,
        "jpgPercentage": 100.0,
        "pngPercentage": 0.0,
        "jpgCount": 1531,
        "pngCount": 0,
        "artistsCount": 635,
        "albumsCount": 1530,
        "tracksCount": 13702,
        "coversCount": 1531,
        "errorsCount": 0,
        "possibleErrors": 369954,
        "purity": 100.0
      }
    },
    {
      "date": "2019-7-17",
      "version": "1.1.0",
      "elapsedSeconds": 0,
      "folderInfo": {
        "name": "/home/messmaker/Data/ManaZeak/Music/_ManaZeakArtists/",
        "files": 16055,
        "folders": 2257,
        "size": 451284950562,
        "flacCount": 14265,
        "mp3Count": 189,
        "flacPercentage": 98.69,
        "mp3Percentage": 1.31,
        "jpgPercentage": 100.0,
        "pngPercentage": 0.0,
        "jpgCount": 1600,
        "pngCount": 0,
        "artistsCount": 659,
        "albumsCount": 1599,
        "tracksCount": 14454,
        "coversCount": 1600,
        "errorsCount": 0,
        "possibleErrors": 390258,
        "purity": 100.0
      }
    },
    {
      "date": "2019-7-24",
      "version": "1.1.0",
      "elapsedSeconds": 0,
      "folderInfo": {
        "name": "/home/messmaker/Data/ManaZeak/Music/_ManaZeakArtists/",
        "files": 17093,
        "folders": 2376,
        "size": 479579659036,
        "flacCount": 15213,
        "mp3Count": 189,
        "flacPercentage": 98.77,
        "mp3Percentage": 1.23,
        "jpgPercentage": 100.0,
        "pngPercentage": 0.0,
        "jpgCount": 1689,
        "pngCount": 0,
        "artistsCount": 689,
        "albumsCount": 1688,
        "tracksCount": 15402,
        "coversCount": 1689,
        "errorsCount": 0,
        "possibleErrors": 415854,
        "purity": 100.0
      }
    },
    {
      "date": "2019-7-31",
      "version": "1.1.3",
      "elapsedSeconds": 0,
      "folderInfo": {
        "name": "/home/messmaker/Data/ManaZeak/Music/_ManaZeakArtists/",
        "files": 17093,
        "folders": 2376,
        "size": 479579659036,
        "flacCount": 15213,
        "mp3Count": 189,
        "flacPercentage": 98.77,
        "mp3Percentage": 1.23,
        "jpgPercentage": 100.0,
        "pngPercentage": 0.0,
        "jpgCount": 1689,
        "pngCount": 0,
        "artistsCount": 689,
        "albumsCount": 1688,
        "tracksCount": 15402,
        "coversCount": 1689,
        "errorsCount": 0,
        "possibleErrors": 415854,
        "purity": 100.0
      }
    },
    {
      "date": "2019-8-7",
      "version": "1.1.3",
      "elapsedSeconds": 0,
      "folderInfo": {
        "name": "/home/messmaker/Data/ManaZeak/Music/_ManaZeakArtists/",
        "files": 17172,
        "folders": 2393,
        "size": 481726002838,
        "flacCount": 15278,
        "mp3Count": 189,
        "flacPercentage": 98.78,
        "mp3Percentage": 1.22,
        "jpgPercentage": 100.0,
        "pngPercentage": 0.0,
        "jpgCount": 1703,
        "pngCount": 0,
        "artistsCount": 692,
        "albumsCount": 1702,
        "tracksCount": 15467,
        "coversCount": 1703,
        "errorsCount": 0,
        "possibleErrors": 417609,
        "purity": 100.0
      }
    },
    {
      "date": "2019-8-14",
      "version": "1.1.3",
      "elapsedSeconds": 0,
      "folderInfo": {
        "name": "/home/messmaker/Data/ManaZeak/Music/_ManaZeakArtists/",
        "files": 17174,
        "folders": 2395,
        "size": 481757389541,
        "flacCount": 15279,
        "mp3Count": 189,
        "flacPercentage": 98.78,
        "mp3Percentage": 1.22,
        "jpgPercentage": 100.0,
        "pngPercentage": 0.0,
        "jpgCount": 1704,
        "pngCount": 0,
        "artistsCount": 693,
        "albumsCount": 1703,
        "tracksCount": 15468,
        "coversCount": 1704,
        "errorsCount": 0,
        "possibleErrors": 417636,
        "purity": 100.0
      }
    },
    {
      "date": "2019-8-21",
      "version": "1.2.0",
      "elapsedSeconds": 0,
      "folderInfo": {
        "name": "/home/messmaker/Data/ManaZeak/Music/_ManaZeakArtists/",
        "files": 17198,
        "folders": 2399,
        "size": 482238736739,
        "flacCount": 15302,
        "mp3Count": 189,
        "flacPercentage": 98.78,
        "mp3Percentage": 1.22,
        "jpgPercentage": 100.0,
        "pngPercentage": 0.0,
        "jpgCount": 1706,
        "pngCount": 0,
        "artistsCount": 695,
        "albumsCount": 1705,
        "tracksCount": 15491,
        "coversCount": 1706,
        "errorsCount": 0,
        "possibleErrors": 418257,
        "purity": 100.0
      }
    },
    {
      "date": "2019-8-28",
      "version": "1.2.1",
      "elapsedSeconds": 428.61,
      "folderInfo": {
        "name": "/home/messmaker/Data/ManaZeak/Music/_ManaZeakArtists/",
        "files": 17198,
        "folders": 2399,
        "size": 482238736739,
        "flacCount": 15302,
        "mp3Count": 189,
        "flacPercentage": 98.78,
        "mp3Percentage": 1.22,
        "jpgPercentage": 100.0,
        "pngPercentage": 0.0,
        "jpgCount": 1706,
        "pngCount": 0,
        "artistsCount": 695,
        "albumsCount": 1705,
        "tracksCount": 15491,
        "coversCount": 1706,
        "errorsCount": 0,
        "possibleErrors": 418257,
        "purity": 100.0
      }
    },
    {
      "date": "2019-9-4",
      "version": "1.2.1",
      "elapsedSeconds": 420.42,
      "folderInfo": {
        "name": "/home/messmaker/Data/ManaZeak/Music/_ManaZeakArtists/",
        "files": 17198,
        "folders": 2399,
        "size": 482238736739,
        "flacCount": 15302,
        "mp3Count": 189,
        "flacPercentage": 98.78,
        "mp3Percentage": 1.22,
        "jpgPercentage": 100.0,
        "pngPercentage": 0.0,
        "jpgCount": 1706,
        "pngCount": 0,
        "artistsCount": 695,
        "albumsCount": 1705,
        "tracksCount": 15491,
        "coversCount": 1706,
        "errorsCount": 0,
        "possibleErrors": 418257,
        "purity": 100.0
      }
    },
    {
      "date": "2019-9-11",
      "version": "1.2.1",
      "elapsedSeconds": 425.83,
      "folderInfo": {
        "name": "/home/messmaker/Data/ManaZeak/Music/_ManaZeakArtists/",
        "files": 17198,
        "folders": 2399,
        "size": 482238736739,
        "flacCount": 15302,
        "mp3Count": 189,
        "flacPercentage": 98.78,
        "mp3Percentage": 1.22,
        "jpgPercentage": 100.0,
        "pngPercentage": 0.0,
        "jpgCount": 1706,
        "pngCount": 0,
        "artistsCount": 695,
        "albumsCount": 1705,
        "tracksCount": 15491,
        "coversCount": 1706,
        "errorsCount": 0,
        "possibleErrors": 418257,
        "purity": 100.0
      }
    },
    {
      "date": "2019-9-18",
      "version": "1.2.1",
      "elapsedSeconds": 445.23,
      "folderInfo": {
        "name": "/home/messmaker/Data/ManaZeak/Music/_ManaZeakArtists/",
        "files": 17556,
        "folders": 2443,
        "size": 492635015420,
        "flacCount": 15630,
        "mp3Count": 189,
        "flacPercentage": 98.81,
        "mp3Percentage": 1.19,
        "jpgPercentage": 100.0,
        "pngPercentage": 0.0,
        "jpgCount": 1736,
        "pngCount": 0,
        "artistsCount": 709,
        "albumsCount": 1735,
        "tracksCount": 15819,
        "coversCount": 1736,
        "errorsCount": 0,
        "possibleErrors": 427113,
        "purity": 100.0
      }
    },
    {
      "date": "2019-9-25",
      "version": "1.2.2",
      "elapsedSeconds": 494.82,
      "folderInfo": {
        "name": "/home/messmaker/Data/ManaZeak/Music/_ManaZeakArtists/",
        "files": 19177,
        "folders": 2675,
        "size": 538378599913,
        "flacCount": 17067,
        "mp3Count": 189,
        "flacPercentage": 98.9,
        "mp3Percentage": 1.1,
        "jpgPercentage": 100.0,
        "pngPercentage": 0.0,
        "jpgCount": 1921,
        "pngCount": 0,
        "artistsCount": 755,
        "albumsCount": 1921,
        "tracksCount": 17256,
        "coversCount": 1921,
        "errorsCount": 0,
        "possibleErrors": 465912,
        "purity": 100.0
      }
    },
    {
      "date": "2019-10-2",
      "version": "1.2.2",
      "elapsedSeconds": 594.63,
      "folderInfo": {
        "name": "/home/messmaker/Data/ManaZeak/Music/_ManaZeakArtists/",
        "files": 21573,
        "folders": 3066,
        "size": 600570560372,
        "flacCount": 19157,
        "mp3Count": 190,
        "flacPercentage": 99.02,
        "mp3Percentage": 0.98,
        "jpgPercentage": 100.0,
        "pngPercentage": 0.0,
        "jpgCount": 2226,
        "pngCount": 0,
        "artistsCount": 841,
        "albumsCount": 2226,
        "tracksCount": 19347,
        "coversCount": 2226,
        "errorsCount": 0,
        "possibleErrors": 522369,
        "purity": 100.0
      }
    },
    {
      "date": "2019-10-9",
      "version": "1.2.2",
      "elapsedSeconds": 608.55,
      "folderInfo": {
        "name": "/home/messmaker/Data/ManaZeak/Music/_ManaZeakArtists/",
        "files": 22657,
        "folders": 3252,
        "size": 630583690324,
        "flacCount": 20119,
        "mp3Count": 190,
        "flacPercentage": 99.06,
        "mp3Percentage": 0.94,
        "jpgPercentage": 100.0,
        "pngPercentage": 0.0,
        "jpgCount": 2348,
        "pngCount": 0,
        "artistsCount": 905,
        "albumsCount": 2348,
        "tracksCount": 20309,
        "coversCount": 2348,
        "errorsCount": 0,
        "possibleErrors": 548343,
        "purity": 100.0
      }
    },
    {
      "date": "2019-10-16",
      "version": "1.2.2",
      "elapsedSeconds": 731.56,
      "folderInfo": {
        "name": "/home/messmaker/Data/ManaZeak/Music/_ManaZeakArtists/",
        "files": 22676,
        "folders": 3254,
        "size": 631412449187,
        "flacCount": 20136,
        "mp3Count": 190,
        "flacPercentage": 99.07,
        "mp3Percentage": 0.93,
        "jpgPercentage": 100.0,
        "pngPercentage": 0.0,
        "jpgCount": 2350,
        "pngCount": 0,
        "artistsCount": 905,
        "albumsCount": 2350,
        "tracksCount": 20326,
        "coversCount": 2350,
        "errorsCount": 0,
        "possibleErrors": 548802,
        "purity": 100.0
      }
    },
    {
      "date": "2019-10-23",
      "version": "1.2.4",
      "elapsedSeconds": 149.64,
      "folderInfo": {
        "name": "D:\\ManaZeak\\Music\\ManaZeakArtists\\",
        "files": 23303,
        "folders": 3336,
        "size": 650460277979,
        "flacCount": 20688,
        "mp3Count": 197,
        "flacPercentage": 99.06,
        "mp3Percentage": 0.94,
        "jpgPercentage": 100.0,
        "pngPercentage": 0.0,
        "jpgCount": 2418,
        "pngCount": 0,
        "artistsCount": 919,
        "albumsCount": 2418,
        "tracksCount": 20885,
        "coversCount": 2418,
        "errorsCount": 0,
        "possibleErrors": 584780,
        "purity": 100.0
      }
    },
    {
      "date": "2019-10-30",
      "version": "1.2.4",
      "elapsedSeconds": 1074.4,
      "folderInfo": {
        "name": "D:\\ManaZeak\\Music\\ManaZeakArtists\\",
        "files": 23452,
        "folders": 3351,
        "size": 652729786275,
        "flacCount": 20823,
        "mp3Count": 197,
        "flacPercentage": 99.06,
        "mp3Percentage": 0.94,
        "jpgPercentage": 100.0,
        "pngPercentage": 0.0,
        "jpgCount": 2432,
        "pngCount": 0,
        "artistsCount": 920,
        "albumsCount": 2432,
        "tracksCount": 21020,
        "coversCount": 2432,
        "errorsCount": 0,
        "possibleErrors": 588560,
        "purity": 100.0
      }
    },
    {
      "date": "2019-11-6",
      "version": "1.2.5",
      "elapsedSeconds": 735.24,
      "folderInfo": {
        "name": "D:\\ManaZeak\\Music\\ManaZeakArtists\\",
        "files": 24983,
        "folders": 3523,
        "size": 690763510882,
        "flacCount": 22221,
        "mp3Count": 197,
        "flacPercentage": 99.12,
        "mp3Percentage": 0.88,
        "jpgPercentage": 100.0,
        "pngPercentage": 0.0,
        "jpgCount": 2565,
        "pngCount": 0,
        "artistsCount": 959,
        "albumsCount": 2565,
        "tracksCount": 22418,
        "coversCount": 2565,
        "errorsCount": 0,
        "possibleErrors": 627704,
        "purity": 100.0
      }
    },
    {
      "date": "2019-11-13",
      "version": "1.2.5",
      "elapsedSeconds": 776.96,
      "folderInfo": {
        "name": "D:\\ManaZeak\\Music\\ManaZeakArtists\\",
        "files": 25830,
        "folders": 3658,
        "size": 711078609302,
        "flacCount": 22952,
        "mp3Count": 197,
        "flacPercentage": 99.15,
        "mp3Percentage": 0.85,
        "jpgPercentage": 100.0,
        "pngPercentage": 0.0,
        "jpgCount": 2681,
        "pngCount": 0,
        "artistsCount": 980,
        "albumsCount": 2679,
        "tracksCount": 23149,
        "coversCount": 2681,
        "errorsCount": 0,
        "possibleErrors": 648172,
        "purity": 100.0
      }
    },
    {
      "date": "2019-11-20",
      "version": "1.2.5",
      "elapsedSeconds": 874.51,
      "folderInfo": {
        "name": "D:\\ManaZeak\\Music\\ManaZeakArtists\\",
        "files": 28157,
        "folders": 4213,
        "size": 767653793552,
        "flacCount": 24785,
        "mp3Count": 197,
        "flacPercentage": 99.21,
        "mp3Percentage": 0.79,
        "jpgPercentage": 100.0,
        "pngPercentage": 0.0,
        "jpgCount": 3175,
        "pngCount": 0,
        "artistsCount": 1039,
        "albumsCount": 3175,
        "tracksCount": 24982,
        "coversCount": 3175,
        "errorsCount": 0,
        "possibleErrors": 699496,
        "purity": 100.0
      }
    },
    {
      "date": "2019-11-27",
      "version": "1.2.5",
      "elapsedSeconds": 833.48,
      "folderInfo": {
        "name": "D:\\ManaZeak\\Music\\ManaZeakArtists\\",
        "files": 28250,
        "folders": 4219,
        "size": 770280703952,
        "flacCount": 24872,
        "mp3Count": 197,
        "flacPercentage": 99.21,
        "mp3Percentage": 0.79,
        "jpgPercentage": 100.0,
        "pngPercentage": 0.0,
        "jpgCount": 3181,
        "pngCount": 0,
        "artistsCount": 1039,
        "albumsCount": 3181,
        "tracksCount": 25069,
        "coversCount": 3181,
        "errorsCount": 0,
        "possibleErrors": 701932,
        "purity": 100.0
      }
    },
    {
      "date": "2019-12-4",
      "version": "1.2.5",
      "elapsedSeconds": 982.12,
      "folderInfo": {
        "name": "D:\\ManaZeak\\Music\\ManaZeakArtists\\",
        "files": 28256,
        "folders": 4220,
        "size": 770470580139,
        "flacCount": 24877,
        "mp3Count": 197,
        "flacPercentage": 99.21,
        "mp3Percentage": 0.79,
        "jpgPercentage": 100.0,
        "pngPercentage": 0.0,
        "jpgCount": 3182,
        "pngCount": 0,
        "artistsCount": 1039,
        "albumsCount": 3182,
        "tracksCount": 25074,
        "coversCount": 3182,
        "errorsCount": 0,
        "possibleErrors": 702072,
        "purity": 100.0
      }
    },
    {
      "date": "2019-12-11",
      "version": "1.2.5",
      "elapsedSeconds": 973.5,
      "folderInfo": {
        "name": "D:\\ManaZeak\\Music\\ManaZeakArtists\\",
        "files": 30108,
        "folders": 4526,
        "size": 821186737416,
        "flacCount": 26458,
        "mp3Count": 197,
        "flacPercentage": 99.26,
        "mp3Percentage": 0.74,
        "jpgPercentage": 100.0,
        "pngPercentage": 0.0,
        "jpgCount": 3453,
        "pngCount": 0,
        "artistsCount": 1074,
        "albumsCount": 3453,
        "tracksCount": 26655,
        "coversCount": 3453,
        "errorsCount": 0,
        "possibleErrors": 746340,
        "purity": 100.0
      }
    },
    {
      "date": "2019-12-18",
      "version": "1.2.5",
      "elapsedSeconds": 2253.19,
      "folderInfo": {
        "name": "D:\\ManaZeak\\Music\\ManaZeakArtists\\",
        "files": 31136,
        "folders": 4733,
        "size": 848716771275,
        "flacCount": 27318,
        "mp3Count": 197,
        "flacPercentage": 99.28,
        "mp3Percentage": 0.72,
        "jpgPercentage": 100.0,
        "pngPercentage": 0.0,
        "jpgCount": 3621,
        "pngCount": 0,
        "artistsCount": 1113,
        "albumsCount": 3621,
        "tracksCount": 27515,
        "coversCount": 3621,
        "errorsCount": 0,
        "possibleErrors": 770420,
        "purity": 100.0
      }
    },
    {
      "date": "2019-12-25",
      "version": "1.2.5",
      "elapsedSeconds": 944.36,
      "folderInfo": {
        "name": "D:\\ManaZeak\\Music\\ManaZeakArtists\\",
        "files": 31435,
        "folders": 4786,
        "size": 856667136718,
        "flacCount": 27573,
        "mp3Count": 197,
        "flacPercentage": 99.29,
        "mp3Percentage": 0.71,
        "jpgPercentage": 100.0,
        "pngPercentage": 0.0,
        "jpgCount": 3665,
        "pngCount": 0,
        "artistsCount": 1122,
        "albumsCount": 3665,
        "tracksCount": 27770,
        "coversCount": 3665,
        "errorsCount": 0,
        "possibleErrors": 777560,
        "purity": 100.0
      }
    },
    {
      "date": "2020-1-1",
      "version": "1.2.5",
      "elapsedSeconds": 944.36,
      "folderInfo": {
        "name": "D:\\ManaZeak\\Music\\ManaZeakArtists\\",
        "files": 31435,
        "folders": 4786,
        "size": 856667136718,
        "flacCount": 27573,
        "mp3Count": 197,
        "flacPercentage": 99.29,
        "mp3Percentage": 0.71,
        "jpgPercentage": 100.0,
        "pngPercentage": 0.0,
        "jpgCount": 3665,
        "pngCount": 0,
        "artistsCount": 1122,
        "albumsCount": 3665,
        "tracksCount": 27770,
        "coversCount": 3665,
        "errorsCount": 0,
        "possibleErrors": 777560,
        "purity": 100.0
      }
    },
    {
      "date": "2020-1-8",
      "version": "1.2.5",
      "elapsedSeconds": 679.14,
      "folderInfo": {
        "name": "D:\\ManaZeak\\Music\\ManaZeakArtists\\",
        "files": 31671,
        "folders": 4834,
        "size": 863070119659,
        "flacCount": 27768,
        "mp3Count": 197,
        "flacPercentage": 99.3,
        "mp3Percentage": 0.7,
        "jpgPercentage": 100.0,
        "pngPercentage": 0.0,
        "jpgCount": 3706,
        "pngCount": 0,
        "artistsCount": 1129,
        "albumsCount": 3706,
        "tracksCount": 27965,
        "coversCount": 3706,
        "errorsCount": 0,
        "possibleErrors": 783020,
        "purity": 100.0
      }
    },
    {
      "date": "2020-1-15",
      "version": "1.2.5",
      "elapsedSeconds": 901.6,
      "folderInfo": {
        "name": "D:\\ManaZeak\\Music\\ManaZeakArtists\\",
        "files": 34259,
        "folders": 5374,
        "size": 929579071940,
        "flacCount": 29905,
        "mp3Count": 197,
        "flacPercentage": 99.35,
        "mp3Percentage": 0.65,
        "jpgPercentage": 100.0,
        "pngPercentage": 0.0,
        "jpgCount": 4157,
        "pngCount": 0,
        "artistsCount": 1218,
        "albumsCount": 4157,
        "tracksCount": 30102,
        "coversCount": 4157,
        "errorsCount": 0,
        "possibleErrors": 842856,
        "purity": 100.0
      }
    },
    {
      "date": "2020-1-22",
      "version": "1.2.5",
      "elapsedSeconds": 1047.15,
      "folderInfo": {
        "name": "D:\\ManaZeak\\Music\\ManaZeakArtists\\",
        "files": 35134,
        "folders": 5557,
        "size": 948946619748,
        "flacCount": 30619,
        "mp3Count": 197,
        "flacPercentage": 99.36,
        "mp3Percentage": 0.64,
        "jpgPercentage": 100.0,
        "pngPercentage": 0.0,
        "jpgCount": 4318,
        "pngCount": 0,
        "artistsCount": 1240,
        "albumsCount": 4318,
        "tracksCount": 30816,
        "coversCount": 4318,
        "errorsCount": 0,
        "possibleErrors": 862848,
        "purity": 100.0
      }
    },
    {
      "date": "2020-1-29",
      "version": "1.2.5",
      "elapsedSeconds": 880.74,
      "folderInfo": {
        "name": "D:\\ManaZeak\\Music\\ManaZeakArtists\\",
        "files": 35380,
        "folders": 5640,
        "size": 955849693411,
        "flacCount": 30875,
        "mp3Count": 125,
        "flacPercentage": 99.6,
        "mp3Percentage": 0.4,
        "jpgPercentage": 100.0,
        "pngPercentage": 0.0,
        "jpgCount": 4380,
        "pngCount": 0,
        "artistsCount": 1260,
        "albumsCount": 4380,
        "tracksCount": 31000,
        "coversCount": 4380,
        "errorsCount": 0,
        "possibleErrors": 868000,
        "purity": 100.0
      }
    },
    {
      "date": "2020-2-5",
      "version": "1.2.5",
      "elapsedSeconds": 1177.36,
      "folderInfo": {
        "name": "D:\\ManaZeak\\Music\\ManaZeakArtists\\",
        "files": 37223,
        "folders": 6073,
        "size": 1004602766100,
        "flacCount": 32401,
        "mp3Count": 103,
        "flacPercentage": 99.68,
        "mp3Percentage": 0.32,
        "jpgPercentage": 100.0,
        "pngPercentage": 0.0,
        "jpgCount": 4719,
        "pngCount": 0,
        "artistsCount": 1354,
        "albumsCount": 4719,
        "tracksCount": 32504,
        "coversCount": 4719,
        "errorsCount": 0,
        "possibleErrors": 910112,
        "purity": 100.0
      }
    },
    {
      "date": "2020-2-12",
      "version": "1.2.5",
      "elapsedSeconds": 1207.66,
      "folderInfo": {
        "name": "D:\\ManaZeak\\Music\\ManaZeakArtists\\",
        "files": 38231,
        "folders": 6274,
        "size": 1031477071998,
        "flacCount": 33252,
        "mp3Count": 81,
        "flacPercentage": 99.76,
        "mp3Percentage": 0.24,
        "jpgPercentage": 100.0,
        "pngPercentage": 0.0,
        "jpgCount": 4898,
        "pngCount": 0,
        "artistsCount": 1376,
        "albumsCount": 4898,
        "tracksCount": 33333,
        "coversCount": 4898,
        "errorsCount": 0,
        "possibleErrors": 933324,
        "purity": 100.0
      }
    },
    {
      "date": "2020-2-19",
      "version": "1.2.5",
      "elapsedSeconds": 1276.57,
      "folderInfo": {
        "name": "D:\\ManaZeak\\Music\\ManaZeakArtists\\",
        "files": 39853,
        "folders": 6644,
        "size": 1070149970239,
        "flacCount": 34543,
        "mp3Count": 72,
        "flacPercentage": 99.79,
        "mp3Percentage": 0.21,
        "jpgPercentage": 100.0,
        "pngPercentage": 0.0,
        "jpgCount": 5238,
        "pngCount": 0,
        "artistsCount": 1406,
        "albumsCount": 5238,
        "tracksCount": 34615,
        "coversCount": 5238,
        "errorsCount": 0,
        "possibleErrors": 969220,
        "purity": 100.0
      }
    },
    {
      "date": "2020-2-26",
      "version": "1.2.5",
      "elapsedSeconds": 1212.01,
      "folderInfo": {
        "name": "D:\\ManaZeak\\Music\\ManaZeakArtists\\",
        "files": 40372,
        "folders": 6772,
        "size": 1082184925839,
        "flacCount": 34957,
        "mp3Count": 68,
        "flacPercentage": 99.81,
        "mp3Percentage": 0.19,
        "jpgPercentage": 100.0,
        "pngPercentage": 0.0,
        "jpgCount": 5347,
        "pngCount": 0,
        "artistsCount": 1425,
        "albumsCount": 5347,
        "tracksCount": 35025,
        "coversCount": 5347,
        "errorsCount": 0,
        "possibleErrors": 980700,
        "purity": 100.0
      }
    },
    {
      "date": "2020-3-4",
      "version": "1.2.6",
      "elapsedSeconds": 1354.29,
      "folderInfo": {
        "name": "D:\\ManaZeak\\Music\\ManaZeakArtists\\",
        "files": 41558,
        "folders": 6999,
        "size": 1111646520495,
        "flacCount": 35945,
        "mp3Count": 68,
        "flacPercentage": 99.81,
        "mp3Percentage": 0.19,
        "jpgPercentage": 100.0,
        "pngPercentage": 0.0,
        "jpgCount": 5545,
        "pngCount": 0,
        "artistsCount": 1454,
        "albumsCount": 5545,
        "tracksCount": 36013,
        "coversCount": 5545,
        "errorsCount": 0,
        "possibleErrors": 1044377,
        "purity": 100.0
      }
    }
  ]
}
